crawler_scraper_common_by_yuvch/__init__.py
crawler_scraper_common_by_yuvch/cleaners.py
crawler_scraper_common_by_yuvch/crawler.py
crawler_scraper_common_by_yuvch/utils.py
crawler_scraper_common_by_yuvch-0.7.1.dist-info/licenses/LICENSE.txt
crawler_scraper_common_by_yuvch-0.7.1.dist-info/METADATA
crawler_scraper_common_by_yuvch-0.7.1.dist-info/WHEEL
crawler_scraper_common_by_yuvch-0.7.1.dist-info/top_level.txt
crawler_scraper_common_by_yuvch-0.7.1.dist-info/RECORD
